winpwn/__init__.py
winpwn/context.py
winpwn/dbg.py
winpwn/misc.py
winpwn/var.py
winpwn/win.py
winpwn/winpwn.py
iospwn-0.0.1.dist-info/METADATA
iospwn-0.0.1.dist-info/WHEEL
iospwn-0.0.1.dist-info/top_level.txt
iospwn-0.0.1.dist-info/RECORD
